{
	"app_state": {
		"assets": {
			"d1984e3d365faa05bcafbe41f50f90e3663ee7c0da22bb1e24b164e9532691b2": {
				"min_lp_stake": "1",
				"decimals": 18,
				"name": "VEGA",
				"symbol": "VEGA",
				"total_supply": "64000000000000000000000000",
				"source": {
				  "erc20": {
					"contract_address": "0xF0598Cd16FA3bf4c34052923cBE2D34028da0c69"
				  }
				}
			  },
			"VOTE": {
				"name": "VOTE",
				"symbol": "VOTE",
				"total_supply": "1000000",
				"decimals": 5,
				"min_lp_stake": "1",
				"source": {
					"builtin_asset": {
						"max_faucet_amount_mint": "100000"
					}
				}
			}
		},
		"network": {
			"ReplayAttackThreshold": 30
		},
		"network_parameters": {
			"validators.epoch.length": "5s",
			"governance.proposal.asset.maxClose": "8760h0m0s",
			"governance.proposal.asset.maxEnact": "8760h0m0s",
			"governance.proposal.asset.minClose": "5s",
			"governance.proposal.asset.minEnact": "5s",
			"governance.proposal.asset.minProposerBalance": "0",
			"governance.proposal.asset.minVoterBalance": "1",
			"governance.proposal.asset.requiredMajority": "0.66",
			"governance.proposal.asset.requiredParticipation": "0.00000000000000000000000015",
			"governance.proposal.market.maxClose": "8760h0m0s",
			"governance.proposal.market.maxEnact": "8760h0m0s",
			"governance.proposal.market.minClose": "5s",
			"governance.proposal.market.minEnact": "5s",
			"governance.proposal.market.minProposerBalance": "0",
			"governance.proposal.market.minVoterBalance": "1",
			"governance.proposal.market.requiredMajority": "0.66",
			"governance.proposal.market.requiredParticipation": "0.00000000000000000000000015",
			"governance.proposal.updateMarket.maxClose": "8760h0m0s",
			"governance.proposal.updateMarket.maxEnact": "8760h0m0s",
			"governance.proposal.updateMarket.minClose": "5s",
			"governance.proposal.updateMarket.minEnact": "5s",
			"governance.proposal.updateMarket.minProposerBalance": "0",
			"governance.proposal.updateMarket.minVoterBalance": "1",
			"governance.proposal.updateMarket.requiredMajority": "0.66",
			"governance.proposal.updateMarket.requiredParticipation": "0.00001",
			"governance.proposal.updateNetParam.maxClose": "8760h0m0s",
			"governance.proposal.updateNetParam.maxEnact": "8760h0m0s",
			"governance.proposal.updateNetParam.minClose": "5s",
			"governance.proposal.updateNetParam.minEnact": "5s",
			"governance.proposal.updateNetParam.minProposerBalance": "0",
			"governance.proposal.updateNetParam.minVoterBalance": "1",
			"governance.proposal.updateNetParam.requiredMajority": "0.66",
			"governance.proposal.updateNetParam.requiredParticipation": "0.00001",
			"market.auction.maximumDuration": "168h0m0s",
			"market.auction.minimumDuration": "1s",
			"market.fee.factors.infrastructureFee": "0.001",
			"market.fee.factors.makerFee": "0.004",
			"market.liquidity.bondPenaltyParameter": "0.1",
			"market.liquidity.maximumLiquidityFeeFactorLevel": "0.3",
			"market.liquidity.targetstake.triggering.ratio": "0",
			"market.liquidityProvision.shapes.maxSize": "10",
			"market.liquidity.stakeToCcySiskas": "0.2",
			"market.margin.scalingFactors": "{\"search_level\": 1.1, \"initial_margin\": 1.2, \"collateral_release\": 1.4}",
			"market.monitor.price.updateFrequency": "4s",
			"market.stake.target.scalingFactor": "5",
			"market.stake.target.timeWindow": "10s",
			"market.value.windowLength": "60s",
			"blockchains.ethereumConfig": "{\"network_id\": \"1\", \"chain_id\": \"1\", \"collateral_bridge_contract\": { \"address\": \"0xCd403f722b76366f7d609842C589906ca051310f\" }, \"staking_bridge_contract\": { \"address\": \"0x195064D33f09e0c42cF98E665D9506e0dC17de68\", \"deployment_block_height\": 0 }, \"token_vesting_contract\": { \"address\": \"0x23d1bFE8fA50a167816fBD79D7932577c06011f4\", \"deployment_block_height\": 0 }, \"confirmations\": 3}"
		},
    "network_limits": {
      "propose_market_enabled": true,
      "propose_asset_enabled": true,
      "propose_market_enabled_from": "2021-08-31T23:59:59Z",
      "propose_asset_enabled_from": "2021-08-31T23:59:59Z"
	}
	},
	"consensus_params": {
		"block": {
			"time_iota_ms": "1"
		}
	}
}